LICENSE
renamer/__init__.py
renamer/__main__.py
renamer/py.typed
python_renamer-0.0.1.dist-info/LICENSE
python_renamer-0.0.1.dist-info/METADATA
python_renamer-0.0.1.dist-info/WHEEL
python_renamer-0.0.1.dist-info/RECORD
